timeflux_dsp/__init__.py
timeflux_dsp/nodes/__init__.py
timeflux_dsp/nodes/filters.py
timeflux_dsp/nodes/helpers.py
timeflux_dsp/nodes/peaks.py
timeflux_dsp/nodes/quality.py
timeflux_dsp/nodes/spectral.py
timeflux_dsp/nodes/squashing.py
timeflux_dsp/nodes/time.py
timeflux_dsp/utils/__init__.py
timeflux_dsp/utils/filters.py
timeflux_dsp/utils/import_helpers.py
timeflux_dsp-0.3.4.dist-info/LICENSE
timeflux_dsp-0.3.4.dist-info/METADATA
timeflux_dsp-0.3.4.dist-info/WHEEL
timeflux_dsp-0.3.4.dist-info/top_level.txt
timeflux_dsp-0.3.4.dist-info/RECORD
